switch_guides_scaffold/__init__.py
switch_guides_scaffold/cli.py
switch_guides_scaffold/scaffolder.py
switch_guides_scaffold/scaffolder_brandon.py
switch_guides_scaffold/guides/__init__.py
switch_guides_scaffold/guides/guides_commands.py
switch_guides_scaffold/taskinsights/__init__.py
switch_guides_scaffold/taskinsights/enums.py
switch_guides_scaffold/taskinsights/task_insights.py
switch_guides_scaffold/taskinsights/transformations.py
switch_guides_scaffold/taskinsights/validation.py
switch_guides_scaffold/taskinsights/templates/__init__.py
switch_guides_scaffold/taskinsights/templates/integrate_csv.py.jinja2
switch_guides_scaffold/taskinsights/templates/python_drivers.py.jinja2
switch_guides_scaffold/templates/__init__.py
switch_guides_scaffold/templates/guide_sample_definition.py
switch_guides_scaffold/templates/guide_sample_step_definition.py
switch_guides_scaffold-0.1.7.dist-info/AUTHORS.rst
switch_guides_scaffold-0.1.7.dist-info/LICENCE
switch_guides_scaffold-0.1.7.dist-info/METADATA
switch_guides_scaffold-0.1.7.dist-info/WHEEL
switch_guides_scaffold-0.1.7.dist-info/entry_points.txt
switch_guides_scaffold-0.1.7.dist-info/top_level.txt
switch_guides_scaffold-0.1.7.dist-info/RECORD
