Metadata-Version: 2.1
Name: switch-guides-scaffold
Version: 0.1.7
Summary: A package for helping with the creation of Platform Guides in Switch Automation Platform.
Home-page: UNKNOWN
Author: Switch Automation Pty Ltd.
License: MIT License
Platform: UNKNOWN
Classifier: Development Status :: 2 - Pre-Alpha
Classifier: License :: OSI Approved :: MIT License
Classifier: Intended Audience :: Other Audience
Classifier: Programming Language :: Python :: 3
Classifier: Programming Language :: Python :: 3.8
Classifier: Programming Language :: Python :: 3.9
Classifier: Natural Language :: English
Requires-Python: >=3.8.*
License-File: LICENCE
License-File: AUTHORS.rst
Requires-Dist: switch-guides
Requires-Dist: click
Requires-Dist: click-help-colors
Requires-Dist: click-spinner
Requires-Dist: pydantic (==1.9.0)
Requires-Dist: jinja2
